[
  {
    "id": "binaryTree",
    "name": "Árvores Binárias",
    "description": "Aprenda sobre árvores binárias, percursos, operações e balanceamento.",
    "classes": [
      {
        "id": "1",
        "name": "Introdução às Árvores Binárias",
        "description": "Entenda o conceito de árvores binárias, sua estrutura e aplicações.",
        "topics": [
          {
            "id": "1",
            "name": "O que são árvores binárias",
            "content": [
              {
                "type": "text",
                "value": "Texto de introdução a arvores binarias"
              },
              {
                "type": "image",
                "value": "https://media.geeksforgeeks.org/wp-content/cdn-uploads/binary-tree-to-DLL.png"
              },
              { "type": "text", "value": "Texto do topico 1 aula 1" }
            ]
          },
          {
            "id": "2",
            "name": "aula 2",
            "content": [
              { "type": "text", "value": "Texto da aula 2 parte 1" },
              {
                "type": "image",
                "value": "https://media.geeksforgeeks.org/wp-content/cdn-uploads/binary-tree-to-DLL.png"
              },
              { "type": "text", "value": "Texto da aula 2 parte 2" }
            ]
          },
          {
            "id": "3",
            "name": "aula 3",
            "content": [
              { "type": "text", "value": "Texto da aula 2 parte 1" },
              {
                "type": "image",
                "value": "https://media.geeksforgeeks.org/wp-content/cdn-uploads/binary-tree-to-DLL.png"
              },
              { "type": "text", "value": "Texto da aula 2 parte 2" }
            ]
          },
          {
            "id": "4",
            "name": "aula 4",
            "content": [
              { "type": "text", "value": "Texto da aula 2 parte 1" },
              {
                "type": "image",
                "value": "https://media.geeksforgeeks.org/wp-content/cdn-uploads/binary-tree-to-DLL.png"
              },
              { "type": "text", "value": "Texto da aula 2 parte 2" }
            ]
          },
          {
            "id": "5",
            "name": "aula 5",
            "content": [
              { "type": "text", "value": "Texto da aula 2 parte 1" },
              {
                "type": "image",
                "value": "https://media.geeksforgeeks.org/wp-content/cdn-uploads/binary-tree-to-DLL.png"
              },
              { "type": "text", "value": "Texto da aula 2 parte 2" }
            ]
          },
          {
            "id": "6",
            "name": "aula 6",
            "content": [
              { "type": "text", "value": "Texto da aula 2 parte 1" },
              {
                "type": "image",
                "value": "https://media.geeksforgeeks.org/wp-content/cdn-uploads/binary-tree-to-DLL.png"
              },
              { "type": "text", "value": "Texto da aula 2 parte 2" }
            ]
          }
        ]
      },
      {
        "id": "2",
        "name": "Percursos em Árvores Binárias",
        "description": "Aprenda sobre os tipos de percursos: pré-ordem, em-ordem e pós-ordem.",
        "topics": [
          {
            "id": "1",
            "name": "aula 1",
            "content": [
              { "type": "text", "value": "Texto da aula 1 parte 1" },
              {
                "type": "image",
                "value": "https://media.geeksforgeeks.org/wp-content/cdn-uploads/binary-tree-to-DLL.png"
              },
              { "type": "text", "value": "Texto da aula 1 parte 2." }
            ]
          },
          {
            "id": "2",
            "name": "aula 2",
            "content": [
              { "type": "text", "value": "Texto da aula 2 parte 1" },
              {
                "type": "image",
                "value": "https://media.geeksforgeeks.org/wp-content/cdn-uploads/binary-tree-to-DLL.png"
              },
              { "type": "text", "value": "Texto da aula 2 parte 2" }
            ]
          }
        ]
      },
      {
        "id": "3",
        "name": "Operações Básicas em Árvores Binárias",
        "description": "Explore operações como inserção, remoção e busca em árvores binárias.",
        "topics": [
          {
            "id": "1",
            "name": "aula 1",
            "content": [
              { "type": "text", "value": "Texto da aula 1 parte 1" },
              {
                "type": "image",
                "value": "https://media.geeksforgeeks.org/wp-content/cdn-uploads/binary-tree-to-DLL.png"
              },
              { "type": "text", "value": "Texto da aula 1 parte 2." }
            ]
          },
          {
            "id": "2",
            "name": "aula 2",
            "content": [
              { "type": "text", "value": "Texto da aula 2 parte 1" },
              {
                "type": "image",
                "value": "https://media.geeksforgeeks.org/wp-content/cdn-uploads/binary-tree-to-DLL.png"
              },
              { "type": "text", "value": "Texto da aula 2 parte 2" }
            ]
          }
        ]
      },
      {
        "id": "4",
        "name": "Árvores Binárias de Busca (BST)",
        "description": "Descubra como as árvores binárias de busca organizam dados de forma eficiente.",
        "topics": [
          {
            "id": "1",
            "name": "aula 1",
            "content": [
              { "type": "text", "value": "Texto da aula 1 parte 1" },
              {
                "type": "image",
                "value": "https://media.geeksforgeeks.org/wp-content/cdn-uploads/binary-tree-to-DLL.png"
              },
              { "type": "text", "value": "Texto da aula 1 parte 2." }
            ]
          },
          {
            "id": "2",
            "name": "aula 2",
            "content": [
              { "type": "text", "value": "Texto da aula 2 parte 1" },
              {
                "type": "image",
                "value": "https://media.geeksforgeeks.org/wp-content/cdn-uploads/binary-tree-to-DLL.png"
              },
              { "type": "text", "value": "Texto da aula 2 parte 2" }
            ]
          }
        ]
      },
      {
        "id": "5",
        "name": "Balanceamento de Árvores Binárias",
        "description": "Saiba por que o balanceamento é importante e como melhorar o desempenho.",
        "topics": [
          {
            "id": "1",
            "name": "aula 1",
            "content": [
              { "type": "text", "value": "Texto da aula 1 parte 1" },
              {
                "type": "image",
                "value": "https://media.geeksforgeeks.org/wp-content/cdn-uploads/binary-tree-to-DLL.png"
              },
              { "type": "text", "value": "Texto da aula 1 parte 2." }
            ]
          },
          {
            "id": "2",
            "name": "aula 2",
            "content": [
              { "type": "text", "value": "Texto da aula 2 parte 1" },
              {
                "type": "image",
                "value": "https://media.geeksforgeeks.org/wp-content/cdn-uploads/binary-tree-to-DLL.png"
              },
              { "type": "text", "value": "Texto da aula 2 parte 2" }
            ]
          }
        ]
      },
      {
        "id": "6",
        "name": "Árvores AVL",
        "description": "Conheça as árvores AVL e como elas mantêm o balanceamento automaticamente.",
        "topics": [
          {
            "id": "1",
            "name": "aula 1",
            "content": [
              { "type": "text", "value": "Texto da aula 1 parte 1" },
              {
                "type": "image",
                "value": "https://media.geeksforgeeks.org/wp-content/cdn-uploads/binary-tree-to-DLL.png"
              },
              { "type": "text", "value": "Texto da aula 1 parte 2." }
            ]
          },
          {
            "id": "2",
            "name": "aula 2",
            "content": [
              { "type": "text", "value": "Texto da aula 2 parte 1" },
              {
                "type": "image",
                "value": "https://media.geeksforgeeks.org/wp-content/cdn-uploads/binary-tree-to-DLL.png"
              },
              { "type": "text", "value": "Texto da aula 2 parte 2" }
            ]
          }
        ]
      },
      {
        "id": "7",
        "name": "Árvores Vermelho-Preto",
        "description": "Entenda como funciona o balanceamento dinâmico nas árvores vermelho-preto.",
        "topics": [
          {
            "id": "1",
            "name": "aula 1",
            "content": [
              { "type": "text", "value": "Texto da aula 1 parte 1" },
              {
                "type": "image",
                "value": "https://media.geeksforgeeks.org/wp-content/cdn-uploads/binary-tree-to-DLL.png"
              },
              { "type": "text", "value": "Texto da aula 1 parte 2." }
            ]
          },
          {
            "id": "2",
            "name": "aula 2",
            "content": [
              { "type": "text", "value": "Texto da aula 2 parte 1" },
              {
                "type": "image",
                "value": "https://media.geeksforgeeks.org/wp-content/cdn-uploads/binary-tree-to-DLL.png"
              },
              { "type": "text", "value": "Texto da aula 2 parte 2" }
            ]
          }
        ]
      },
      {
        "id": "8",
        "name": "Casos de Uso e Aplicações",
        "description": "Veja como árvores binárias são usadas em bancos de dados, IA e mais.",
        "topics": [
          {
            "id": "1",
            "name": "aula 1",
            "content": [
              { "type": "text", "value": "Texto da aula 1 parte 1" },
              {
                "type": "image",
                "value": "https://media.geeksforgeeks.org/wp-content/cdn-uploads/binary-tree-to-DLL.png"
              },
              { "type": "text", "value": "Texto da aula 1 parte 2." }
            ]
          },
          {
            "id": "2",
            "name": "aula 2",
            "content": [
              { "type": "text", "value": "Texto da aula 2 parte 1" },
              {
                "type": "image",
                "value": "https://media.geeksforgeeks.org/wp-content/cdn-uploads/binary-tree-to-DLL.png"
              },
              { "type": "text", "value": "Texto da aula 2 parte 2" }
            ]
          }
        ]
      }
    ]
  },
  {
    "id": "stack",
    "name": "Tabelas Hash",
    "description": "Aprenda sobre tabelas hash.",
    "classes": [
      {
        "id": "1",
        "name": "Introdução à Tabelas Hash",
        "description": "Entenda o conceito de tabelas hash, sua estrutura e aplicações.",
        "topics": [
          {
            "id": "1",
            "name": "O que são tabelas hash",
            "content": [
              {
                "type": "text",
                "value": "Texto de introdução a tabelas hash"
              },
              {
                "type": "image",
                "value": "https://media.geeksforgeeks.org/wp-content/cdn-uploads/binary-tree-to-DLL.png"
              },
              { "type": "text", "value": "Texto do topico 1 aula 1" }
            ]
          },
          {
            "id": "2",
            "name": "aula 2",
            "content": [
              { "type": "text", "value": "Texto da aula 2 parte 1" },
              {
                "type": "image",
                "value": "https://media.geeksforgeeks.org/wp-content/cdn-uploads/binary-tree-to-DLL.png"
              },
              { "type": "text", "value": "Texto da aula 2 parte 2" }
            ]
          },
          {
            "id": "3",
            "name": "aula 3",
            "content": [
              { "type": "text", "value": "Texto da aula 2 parte 1" },
              {
                "type": "image",
                "value": "https://media.geeksforgeeks.org/wp-content/cdn-uploads/binary-tree-to-DLL.png"
              },
              { "type": "text", "value": "Texto da aula 2 parte 2" }
            ]
          },
          {
            "id": "4",
            "name": "aula 4",
            "content": [
              { "type": "text", "value": "Texto da aula 2 parte 1" },
              {
                "type": "image",
                "value": "https://media.geeksforgeeks.org/wp-content/cdn-uploads/binary-tree-to-DLL.png"
              },
              { "type": "text", "value": "Texto da aula 2 parte 2" }
            ]
          },
          {
            "id": "5",
            "name": "aula 5",
            "content": [
              { "type": "text", "value": "Texto da aula 2 parte 1" },
              {
                "type": "image",
                "value": "https://media.geeksforgeeks.org/wp-content/cdn-uploads/binary-tree-to-DLL.png"
              },
              { "type": "text", "value": "Texto da aula 2 parte 2" }
            ]
          },
          {
            "id": "6",
            "name": "aula 6",
            "content": [
              { "type": "text", "value": "Texto da aula 2 parte 1" },
              {
                "type": "image",
                "value": "https://media.geeksforgeeks.org/wp-content/cdn-uploads/binary-tree-to-DLL.png"
              },
              { "type": "text", "value": "Texto da aula 2 parte 2" }
            ]
          }
        ]
      },
      {
        "id": "2",
        "name": "Pilhas 2",
        "description": "Aprenda sobre os tipos de percursos: pré-ordem, em-ordem e pós-ordem.",
        "topics": [
          {
            "id": "1",
            "name": "aula 1",
            "content": [
              { "type": "text", "value": "Texto da aula 1 parte 1" },
              {
                "type": "image",
                "value": "https://media.geeksforgeeks.org/wp-content/cdn-uploads/binary-tree-to-DLL.png"
              },
              { "type": "text", "value": "Texto da aula 1 parte 2." }
            ]
          },
          {
            "id": "2",
            "name": "aula 2",
            "content": [
              { "type": "text", "value": "Texto da aula 2 parte 1" },
              {
                "type": "image",
                "value": "https://media.geeksforgeeks.org/wp-content/cdn-uploads/binary-tree-to-DLL.png"
              },
              { "type": "text", "value": "Texto da aula 2 parte 2" }
            ]
          }
        ]
      },
      {
        "id": "3",
        "name": "Pilhas 3",
        "description": "Explore operações como inserção, remoção e busca em árvores binárias.",
        "topics": [
          {
            "id": "1",
            "name": "aula 1",
            "content": [
              { "type": "text", "value": "Texto da aula 1 parte 1" },
              {
                "type": "image",
                "value": "https://media.geeksforgeeks.org/wp-content/cdn-uploads/binary-tree-to-DLL.png"
              },
              { "type": "text", "value": "Texto da aula 1 parte 2." }
            ]
          },
          {
            "id": "2",
            "name": "aula 2",
            "content": [
              { "type": "text", "value": "Texto da aula 2 parte 1" },
              {
                "type": "image",
                "value": "https://media.geeksforgeeks.org/wp-content/cdn-uploads/binary-tree-to-DLL.png"
              },
              { "type": "text", "value": "Texto da aula 2 parte 2" }
            ]
          }
        ]
      },
      {
        "id": "4",
        "name": "Pilhas 4",
        "description": "Descubra como as árvores binárias de busca organizam dados de forma eficiente.",
        "topics": [
          {
            "id": "1",
            "name": "aula 1",
            "content": [
              { "type": "text", "value": "Texto da aula 1 parte 1" },
              {
                "type": "image",
                "value": "https://media.geeksforgeeks.org/wp-content/cdn-uploads/binary-tree-to-DLL.png"
              },
              { "type": "text", "value": "Texto da aula 1 parte 2." }
            ]
          },
          {
            "id": "2",
            "name": "aula 2",
            "content": [
              { "type": "text", "value": "Texto da aula 2 parte 1" },
              {
                "type": "image",
                "value": "https://media.geeksforgeeks.org/wp-content/cdn-uploads/binary-tree-to-DLL.png"
              },
              { "type": "text", "value": "Texto da aula 2 parte 2" }
            ]
          }
        ]
      }
    ]
  }
]
